dfo_ls-1.6.2.dist-info/licenses/LICENSE.txt
dfols/__init__.py
dfols/controller.py
dfols/diagnostic_info.py
dfols/evaluations_database.py
dfols/hessian.py
dfols/model.py
dfols/params.py
dfols/solver.py
dfols/trust_region.py
dfols/util.py
dfo_ls-1.6.2.dist-info/METADATA
dfo_ls-1.6.2.dist-info/WHEEL
dfo_ls-1.6.2.dist-info/top_level.txt
dfo_ls-1.6.2.dist-info/RECORD
